secure_string/__init__.py
secure_string/secure_string_context.py
secure_string/secure_string_exceptions.py
secure_string/secure_string_itself.py
secure_string/secure_string_strict_context.py
secure_string/secure_string_strict_exceptions.py
secure_strings-1.0.4.dist-info/LICENSE
secure_strings-1.0.4.dist-info/METADATA
secure_strings-1.0.4.dist-info/WHEEL
secure_strings-1.0.4.dist-info/top_level.txt
secure_strings-1.0.4.dist-info/RECORD
